corpus_reader/__init__.py
corpus_reader/corpus_reader.py
corpus_reader-0.0.3.dist-info/METADATA
corpus_reader-0.0.3.dist-info/WHEEL
corpus_reader-0.0.3.dist-info/top_level.txt
corpus_reader-0.0.3.dist-info/RECORD
